{
  "match_id": 537397,
  "home_team": "Argentina",
  "away_team": "Algeria",
  "stage": "group",
  "group": "J",
  "utc_date": "2026-06-17T01:00:00Z",
  "probs": {
    "p_home": 0.6403,
    "p_draw": 0.2629,
    "p_away": 0.0968
  },
  "top_scorelines": [
    {
      "home": 1,
      "away": 0,
      "prob": 0.1493
    },
    {
      "home": 2,
      "away": 0,
      "prob": 0.1297
    },
    {
      "home": 1,
      "away": 1,
      "prob": 0.1232
    },
    {
      "home": 2,
      "away": 1,
      "prob": 0.1008
    },
    {
      "home": 0,
      "away": 0,
      "prob": 0.0913
    }
  ],
  "shap": [
    {
      "feature": "Elo rating gap",
      "impact": 0.6295,
      "direction": "favors"
    },
    {
      "feature": "neutral venue",
      "impact": -0.096,
      "direction": "against"
    },
    {
      "feature": "away Elo",
      "impact": -0.0909,
      "direction": "against"
    },
    {
      "feature": "away strength of schedule",
      "impact": -0.0819,
      "direction": "against"
    },
    {
      "feature": "head-to-head goal margin",
      "impact": 0.0431,
      "direction": "favors"
    },
    {
      "feature": "away momentum (1yr Elo)",
      "impact": 0.0361,
      "direction": "favors"
    }
  ],
  "form": {
    "home": [
      "D",
      "W",
      "L",
      "W",
      "W",
      "W",
      "W",
      "W",
      "W",
      "W"
    ],
    "away": [
      "D",
      "W",
      "W",
      "W",
      "W",
      "L",
      "W",
      "D",
      "W",
      "W"
    ]
  },
  "h2h": {
    "meetings": 1,
    "home_wins": 1,
    "away_wins": 0,
    "draws": 0
  },
  "elo_history": {
    "home": [
      {
        "date": "2022-02",
        "elo": 2178.9
      },
      {
        "date": "2022-03",
        "elo": 2172.4
      },
      {
        "date": "2022-06",
        "elo": 2190.5
      },
      {
        "date": "2022-09",
        "elo": 2193.1
      },
      {
        "date": "2022-11",
        "elo": 2175.5
      },
      {
        "date": "2022-12",
        "elo": 2204.5
      },
      {
        "date": "2023-03",
        "elo": 2206.3
      },
      {
        "date": "2023-06",
        "elo": 2210.7
      },
      {
        "date": "2023-09",
        "elo": 2219.8
      },
      {
        "date": "2023-10",
        "elo": 2233.0
      },
      {
        "date": "2023-11",
        "elo": 2202.8
      },
      {
        "date": "2024-03",
        "elo": 2205.4
      },
      {
        "date": "2024-06",
        "elo": 2227.9
      },
      {
        "date": "2024-07",
        "elo": 2238.9
      },
      {
        "date": "2024-09",
        "elo": 2220.3
      },
      {
        "date": "2024-10",
        "elo": 2210.8
      },
      {
        "date": "2024-11",
        "elo": 2179.4
      },
      {
        "date": "2025-03",
        "elo": 2212.3
      },
      {
        "date": "2025-06",
        "elo": 2203.8
      },
      {
        "date": "2025-09",
        "elo": 2181.5
      },
      {
        "date": "2025-10",
        "elo": 2183.8
      },
      {
        "date": "2025-11",
        "elo": 2185.5
      },
      {
        "date": "2026-03",
        "elo": 2186.2
      },
      {
        "date": "2026-06",
        "elo": 2189.2
      }
    ],
    "away": [
      {
        "date": "2022-03",
        "elo": 1784.2
      },
      {
        "date": "2022-06",
        "elo": 1816.0
      },
      {
        "date": "2022-09",
        "elo": 1823.1
      },
      {
        "date": "2022-11",
        "elo": 1809.4
      },
      {
        "date": "2023-03",
        "elo": 1813.9
      },
      {
        "date": "2023-06",
        "elo": 1817.1
      },
      {
        "date": "2023-09",
        "elo": 1813.9
      },
      {
        "date": "2023-10",
        "elo": 1818.3
      },
      {
        "date": "2023-11",
        "elo": 1831.4
      },
      {
        "date": "2024-01",
        "elo": 1771.4
      },
      {
        "date": "2024-03",
        "elo": 1771.3
      },
      {
        "date": "2024-06",
        "elo": 1750.4
      },
      {
        "date": "2024-09",
        "elo": 1776.4
      },
      {
        "date": "2024-10",
        "elo": 1793.0
      },
      {
        "date": "2024-11",
        "elo": 1792.2
      },
      {
        "date": "2025-03",
        "elo": 1815.4
      },
      {
        "date": "2025-06",
        "elo": 1811.6
      },
      {
        "date": "2025-09",
        "elo": 1804.1
      },
      {
        "date": "2025-10",
        "elo": 1809.3
      },
      {
        "date": "2025-11",
        "elo": 1827.4
      },
      {
        "date": "2025-12",
        "elo": 1867.3
      },
      {
        "date": "2026-01",
        "elo": 1839.6
      },
      {
        "date": "2026-03",
        "elo": 1855.3
      },
      {
        "date": "2026-06",
        "elo": 1883.1
      }
    ]
  },
  "venue": null
}